am_i_normal/__init__.py
am_i_normal/is_normal.py
am_i_normal-0.1.1.dist-info/METADATA
am_i_normal-0.1.1.dist-info/WHEEL
am_i_normal-0.1.1.dist-info/top_level.txt
am_i_normal-0.1.1.dist-info/RECORD
